ExtGUIAPI/RichTUILIB.cp310-win_amd64.pyd
ExtGUIAPI/RichTUILIB.pyi
ExtGUIAPI/__init__.py
ExtGUIAPI/out/ExtGUIAPI/RichTUILIB.pyi
extguiapi-1.2601.802.dist-info/licenses/LICENSE
extguiapi-1.2601.802.dist-info/METADATA
extguiapi-1.2601.802.dist-info/WHEEL
extguiapi-1.2601.802.dist-info/top_level.txt
extguiapi-1.2601.802.dist-info/RECORD
